{
  "exploration_id": "v004-retro-006-learnings-1770618686665",
  "results_folder": "v004-retro-006-learnings",
  "status": "complete",
  "pid": 21620,
  "started_at": "2026-02-09T06:31:26.665556",
  "updated_at": "2026-02-09T06:38:36.345000",
  "completed_at": "2026-02-09T06:38:36.344410",
  "error": null,
  "documents": [
    "README.md",
    "learnings-detail.md"
  ],
  "committed": true,
  "commit_error": null,
  "prompt_path": "comms/inbox/exploration/v004-retro-006-learnings/prompt.md",
  "outbox_path": "comms/outbox/exploration/v004-retro-006-learnings"
}